Workbook

Sheet Product Backlog
A1: KontadorIA · Product Backlog
A2: Lista ordenada: el orden refleja la prioridad (1 = se trabaja primero). Responsable del orden: Product Owner (Vicente Hermosilla). Actualizado: 11-10-2026. Sincronizado con Jira (proyecto KONTADORIA).
A4: Orden | B4: ID | C4: Jira | D4: Ítem | E4: Historia de usuario (Como… quiero… para…) | F4: Módulo | G4: Rol | H4: Prioridad | I4: Puntos | J4: Sprint | K4: Estado | L4: Depende de | M4: Requisitos (RF)
A5: 1 | B5: HU17 | C5: KONTADORIA-17 | D5: Registro de cuenta y empresa | E5: Como dueño de una PYME, quiero crear mi cuenta y registrar mi empresa, para empezar a usar KontadorIA. | F5: Acceso y empresa | G5: Dueño (nuevo) | H5: Alta | I5: 5 | J5: Sprint 1 — Base y acceso | K5: Por hacer | L5: — | M5: RF20
A6: 2 | B6: HU01 | C6: KONTADORIA-1 | D6: Inicio de sesión | E6: Como usuario de KontadorIA, quiero iniciar sesión con mi correo y contraseña, para acceder de forma segura a las funcionalidades de mi empresa. | F6: Acceso y empresa | G6: Todos | H6: Alta | I6: 3 | J6: Sprint 1 — Base y acceso | K6: Por hacer | L6: HU17 | M6: RF01
A7: 3 | B7: HU05 | C7: KONTADORIA-5 | D7: Aislamiento de información | E7: Como usuario de una empresa, quiero acceder solo a la información que me corresponde, para mantener protegidos los datos financieros. | F7: Seguridad | G7: Todos | H7: Alta | I7: 5 | J7: Sprint 1 — Base y acceso | K7: Por hacer | L7: HU01 | M7: RF05
A8: 4 | B8: HU04 | C8: KONTADORIA-4 | D8: Gestión de empresas | E8: Como administrador, quiero gestionar la información de mi empresa, para mantenerla correctamente identificada en la plataforma. | F8: Acceso y empresa | G8: Administrador | H8: Media | I8: 5 | J8: Sprint 1 — Base y acceso | K8: Por hacer | L8: HU17 | M8: RF04
A9: 5 | B9: HU03 | C9: KONTADORIA-3 | D9: Roles y permisos | E9: Como administrador, quiero que cada usuario tenga permisos según su rol, para controlar qué información y funcionalidades puede usar. | F9: Seguridad | G9: Administrador | H9: Alta | I9: 5 | J9: Sprint 2 — Equipo y registro | K9: Por hacer | L9: HU01, HU05 | M9: RF03
A10: 6 | B10: HU14 | C10: KONTADORIA-14 | D10: Gestión de categorías | E10: Como administrador, quiero gestionar las categorías de ingresos y gastos, para organizar los movimientos financieros. | F10: Movimientos | G10: Administrador | H10: Alta | I10: 3 | J10: Sprint 2 — Equipo y registro | K10: Por hacer | L10: HU03 | M10: RF17
A11: 7 | B11: HU02 | C11: KONTADORIA-2 | D11: Gestión de usuarios | E11: Como administrador, quiero invitar y gestionar a los usuarios de mi empresa, para que otras personas usen la plataforma con su rol. | F11: Acceso y empresa | G11: Administrador | H11: Media | I11: 5 | J11: Sprint 2 — Equipo y registro | K11: Por hacer | L11: HU17, HU03 | M11: RF02
A12: 8 | B12: HU06 | C12: KONTADORIA-6 | D12: Registrar ingresos y gastos | E12: Como administrador o empleado, quiero registrar ingresos y gastos manualmente, para mantener actualizado el control financiero. | F12: Movimientos | G12: Administrador, empleado | H12: Alta | I12: 5 | J12: Sprint 2 — Equipo y registro | K12: Por hacer | L12: HU14, HU05 | M12: RF06, RF08
A13: 9 | B13: HU07 | C13: KONTADORIA-7 | D13: Consultar y filtrar movimientos | E13: Como usuario, quiero consultar y filtrar movimientos, para encontrar rápidamente la información que necesito. | F13: Movimientos | G13: Todos | H13: Alta | I13: 5 | J13: Sprint 2 — Equipo y registro | K13: Por hacer | L13: HU06 | M13: RF07
A14: 10 | B14: HU08 | C14: KONTADORIA-8 | D14: Cargar boleta o factura | E14: Como administrador o empleado, quiero cargar una boleta o factura por imagen o PDF, para registrarla sin tipear los datos. | F14: Carga con IA | G14: Administrador, empleado | H14: Alta | I14: 5 | J14: Sprint 3 — IA y dashboard | K14: Por hacer | L14: HU06 | M14: RF09, RF10, RF12
A15: 11 | B15: HU09 | C15: KONTADORIA-9 | D15: Validar información extraída | E15: Como usuario, quiero revisar y corregir la información extraída por la IA, para asegurar que el movimiento se registre correctamente. | F15: Carga con IA | G15: Administrador, empleado | H15: Alta | I15: 5 | J15: Sprint 3 — IA y dashboard | K15: Por hacer | L15: HU08 | M15: RF11
A16: 12 | B16: HU18 | C16: KONTADORIA-18 | D16: Dashboard | E16: Como usuario, quiero ver un resumen de los ingresos y gastos, para entender rápidamente la situación financiera. | F16: Reportes | G16: Todos | H16: Media | I16: 5 | J16: Sprint 3 — IA y dashboard | K16: Por hacer | L16: HU06, HU14 | M16: RF21
... A22: 18 | B22: HU15 | C22: KONTADORIA-15 | D22: Gestión de presupuestos | E22: Como administrador, quiero definir presupuestos por categoría y mes, para controlar los límites de gasto. | F22: Reportes | G22: Administrador | H22: Baja | I22: 5 | J22: Sprint 5 — Finanzas y cierre | K22: Por hacer | L22: HU14 | M22: RF18
A24: Notas: D1 resuelta → el contador no registra movimientos (HU06, HU08, HU09). D2 resuelta → solo el administrador crea categorías (HU09, HU14). HU17 y HU18 estimadas en 5 pts. HU14 pasa al Sprint 2 (11-10-2026); la migración de categorías predefinidas queda en HU17, Sprint 1. Requisitos según la Planilla de Requerimientos v2. Las subtareas técnicas de cada historia están en Jira.

Sheet Resumen
A1: Resumen del backlog
A2: Todo se calcula desde la hoja Product Backlog; no editar.
A4: Por estado
A5: Estado | B5: Historias | C5: Puntos | D5: % de puntos
A6: Por hacer | B6: =COUNTIF('Product Backlog'!$K$5:$K$52,A6) | C6: =SUMIF('Product Backlog'!$K$5:$K$52,A6,'Product Backlog'!$I$5:$I$52) | D6: =IF(SUM($C$6:$C$9)=0,0,C6/SUM($C$6:$C$9))
A7: En progreso | B7: =COUNTIF('Product Backlog'!$K$5:$K$52,A7) | C7: =SUMIF('Product Backlog'!$K$5:$K$52,A7,'Product Backlog'!$I$5:$I$52) | D7: =IF(SUM($C$6:$C$9)=0,0,C7/SUM($C$6:$C$9))
A8: En revisión | B8: =COUNTIF('Product Backlog'!$K$5:$K$52,A8) | C8: =SUMIF('Product Backlog'!$K$5:$K$52,A8,'Product Backlog'!$I$5:$I$52) | D8: =IF(SUM($C$6:$C$9)=0,0,C8/SUM($C$6:$C$9))
A9: Hecho | B9: =COUNTIF('Product Backlog'!$K$5:$K$52,A9) | C9: =SUMIF('Product Backlog'!$K$5:$K$52,A9,'Product Backlog'!$I$5:$I$52) | D9: =IF(SUM($C$6:$C$9)=0,0,C9/SUM($C$6:$C$9))
A10: Total | B10: =SUM(B6:B9) | C10: =SUM(C6:C9) | D10: =SUM(D6:D9)
A12: Por sprint
A13: Sprint | B13: Historias | C13: Puntos | D13: % de puntos
A14: Sprint 1 — Base y acceso | B14: =COUNTIF('Product Backlog'!$J$5:$J$52,A14) | C14: =SUMIF('Product Backlog'!$J$5:$J$52,A14,'Product Backlog'!$I$5:$I$52) | D14: =IF(SUM($C$14:$C$18)=0,0,C14/SUM($C$14:$C$18))
A15: Sprint 2 — Equipo y registro | B15: =COUNTIF('Product Backlog'!$J$5:$J$52,A15) | C15: =SUMIF('Product Backlog'!$J$5:$J$52,A15,'Product Backlog'!$I$5:$I$52) | D15: =IF(SUM($C$14:$C$18)=0,0,C15/SUM($C$14:$C$18))
A16: Sprint 3 — IA y dashboard | B16: =COUNTIF('Product Backlog'!$J$5:$J$52,A16) | C16: =SUMIF('Product Backlog'!$J$5:$J$52,A16,'Product Backlog'!$I$5:$I$52) | D16: =IF(SUM($C$14:$C$18)=0,0,C16/SUM($C$14:$C$18))
A17: Sprint 4 — Importación masiva | B17: =COUNTIF('Product Backlog'!$J$5:$J$52,A17) | C17: =SUMIF('Product Backlog'!$J$5:$J$52,A17,'Product Backlog'!$I$5:$I$52) | D17: =IF(SUM($C$14:$C$18)=0,0,C17/SUM($C$14:$C$18))
A18: Sprint 5 — Finanzas y cierre | B18: =COUNTIF('Product Backlog'!$J$5:$J$52,A18) | C18: =SUMIF('Product Backlog'!$J$5:$J$52,A18,'Product Backlog'!$I$5:$I$52) | D18: =IF(SUM($C$14:$C$18)=0,0,C18/SUM($C$14:$C$18))
A19: Total | B19: =SUM(B14:B18) | C19: =SUM(C14:C18) | D19: =SUM(D14:D18)
A21: Por prioridad
A22: Prioridad | B22: Historias | C22: Puntos | D22: % de puntos
A23: Alta | B23: =COUNTIF('Product Backlog'!$H$5:$H$52,A23) | C23: =SUMIF('Product Backlog'!$H$5:$H$52,A23,'Product Backlog'!$I$5:$I$52) | D23: =IF(SUM($C$23:$C$25)=0,0,C23/SUM($C$23:$C$25))
A24: Media | B24: =COUNTIF('Product Backlog'!$H$5:$H$52,A24) | C24: =SUMIF('Product Backlog'!$H$5:$H$52,A24,'Product Backlog'!$I$5:$I$52) | D24: =IF(SUM($C$23:$C$25)=0,0,C24/SUM($C$23:$C$25))
A25: Baja | B25: =COUNTIF('Product Backlog'!$H$5:$H$52,A25) | C25: =SUMIF('Product Backlog'!$H$5:$H$52,A25,'Product Backlog'!$I$5:$I$52) | D25: =IF(SUM($C$23:$C$25)=0,0,C25/SUM($C$23:$C$25))
A26: Total | B26: =SUM(B23:B25) | C26: =SUM(C23:C25) | D26: =SUM(D23:D25)

Sheet Backlog futuro
A1: Backlog futuro (fuera de la versión 1)
A2: Ideas registradas para no perderlas; no se estiman ni se planifican en el Capstone.
A4: ID | B4: Ítem | C4: Motivo para dejarlo fuera de v1
A5: BF01 | B5: Integración con el SII | C5: Complejidad regulatoria y técnica; fuera del alcance acordado.
A6: BF02 | B6: Sincronización con bancos | C6: Requiere convenios/APIs bancarias; fuera del alcance acordado.
A7: BF03 | B7: Montos en otras monedas | C7: v1 trabaja solo en CLP, montos enteros.
A8: BF04 | B8: Aplicación móvil nativa | C8: Se cubre con web responsive instalable como PWA.
A9: BF05 | B9: Envío automático de correos de invitación | C9: En v1 el administrador comparte el link manualmente (HU02).
A10: BF06 | B10: Alertas al acercarse al límite del presupuesto | C10: Extensión de HU15; se prioriza después de v1.

Sheet Leyenda
A1: Cómo mantener este backlog
A3: Campo | B3: Significado
A4: Orden | B4: Posición en la lista. Para repriorizar, mover la fila completa y renumerar.
A5: Prioridad | B5: Alta = necesaria para que el producto funcione; Media = parte del alcance v1; Baja = se puede postergar si falta tiempo.
A6: Puntos | B6: Estimación relativa de esfuerzo (Fibonacci: 1, 2, 3, 5, 8, 13). La estima el Desarrollador.
A7: Sprint | B7: Sprint de Jira en que se planifica la historia (2 semanas cada uno; fechas y Sprint Goal en Jira y en el Sprint Backlog).
A8: Estado | B8: Por hacer · En progreso · En revisión · Hecho. Se actualiza al cierre de cada Sprint.
A9: Depende de | B9: Historias que deben estar terminadas antes.
A10: Requisitos (RF) | B10: Requisito funcional de la Planilla de Requerimientos que cubre la historia.
A11: Columnas editables | B11: Orden, Prioridad, Puntos, Sprint, Estado y Depende de. La hoja Resumen se calcula sola.
A12: Criterios de aceptación | B12: Están en el documento Historias de Usuario v1.1 y en cada ticket de Jira.
